odbp/__init__.py
odbp/data_model.py
odbp/magic.py
odbp/odbp.py
odbp/odbp_settings.py
odbp/reader.py
odbp/writer.py
odbp/data/config.toml
odbp/data/odbp_views.toml
odbp/py2_scripts/converter.py
odbp/py2_scripts/odb_info_getter.py
odbp-1.1.3.dist-info/LICENSE
odbp-1.1.3.dist-info/METADATA
odbp-1.1.3.dist-info/WHEEL
odbp-1.1.3.dist-info/top_level.txt
odbp-1.1.3.dist-info/RECORD
