Metadata-Version: 2.1
Name: odbp
Version: 1.1.3
Summary: Python3 API for Abaqus .odb files. Focused on Additive Manufacturing Thermal Transfer
Author-email: Clark Hensley <clarkhensley@duck.com>
Maintainer-email: Clark Hensley <clarkhensley@duck.com>
License: MIT License
Project-URL: Homepage, https://www.cmml.me.msstate.edu
Project-URL: Bug Reports, https://www.github.com/Computational-Mechanics-Materials-Lab/ODBP/issues
Project-URL: Source, https://www.github.com/Computational-Mechanics-Materials-Lab/ODBP
Keywords: abaqus,abq,fea,odb,waam,wa-ded,visualization
License-File: LICENSE
Requires-Dist: platformdirs
Requires-Dist: h5py
Requires-Dist: numpy
Requires-Dist: pandas
Requires-Dist: pyreadline3 ; platform_system == "Windows"
Provides-Extra: all
Requires-Dist: odbp[plot] ; extra == 'all'
Provides-Extra: plot
Requires-Dist: polyscope ; extra == 'plot'
Requires-Dist: scipy ; extra == 'plot'
Requires-Dist: tomli >=1.1.0 ; (python_version < "3.11") and extra == 'plot'
